LICENSE
README.md
pyproject.toml
setup.py
./arduino_coldfire_bdm/arduino-coldfire-bdm.ino
./arduino_coldfire_bdm/bdm_interface.py
./arduino_coldfire_bdm/command_line.py
./arduino_coldfire_bdm/control_registers.py
./arduino_coldfire_bdm/serial_interface.py
arduino_coldfire_bdm/bdm_interface.py
arduino_coldfire_bdm/command_line.py
arduino_coldfire_bdm/control_registers.py
arduino_coldfire_bdm/serial_interface.py
arduino_coldfire_bdm.egg-info/PKG-INFO
arduino_coldfire_bdm.egg-info/SOURCES.txt
arduino_coldfire_bdm.egg-info/dependency_links.txt
arduino_coldfire_bdm.egg-info/entry_points.txt
arduino_coldfire_bdm.egg-info/requires.txt
arduino_coldfire_bdm.egg-info/top_level.txt