Metadata-Version: 2.1
Name: arduino-coldfire-bdm
Version: 0.1.0
Summary: An interface to Motorola® Coldfire processors' Background Debug Interface (BDM) using an Arduino.
Home-page: https://github.com/psobot/arduino_coldfire_bdm
Author: Peter Sobot
Author-email: github@petersobot.com
Keywords: coldfire,bdm,debugger,68k,motorola,arduino
Classifier: Development Status :: 3 - Alpha
Classifier: Intended Audience :: Developers
Classifier: Topic :: Software Development :: Debuggers
Classifier: License :: OSI Approved :: MIT License
Classifier: Programming Language :: Python :: 3
Classifier: Programming Language :: Python :: 3.7
Classifier: Programming Language :: Python :: 3.8
Classifier: Programming Language :: Python :: 3.9
Classifier: Programming Language :: Python :: 3.10
Classifier: Programming Language :: Python :: 3.11
Classifier: Programming Language :: Python :: 3 :: Only
Requires-Python: >=3.6, <4
License-File: LICENSE
